ReactXuexiZhidao/README.md
ReactXuexiZhidao/__init__.py
ReactXuexiZhidao/__main__.py
ReactXuexiZhidao/file.epub
ReactXuexiZhidao/index.html
ReactXuexiZhidao/css/__init__.py
ReactXuexiZhidao/css/annotations.css
ReactXuexiZhidao/css/main.css
ReactXuexiZhidao/css/normalize.css
ReactXuexiZhidao/css/popup.css
ReactXuexiZhidao/font/__init__.py
ReactXuexiZhidao/font/fontello.eot
ReactXuexiZhidao/font/fontello.svg
ReactXuexiZhidao/font/fontello.ttf
ReactXuexiZhidao/font/fontello.woff
ReactXuexiZhidao/img/__init__.py
ReactXuexiZhidao/img/annotator-glyph-sprite.png
ReactXuexiZhidao/img/annotator-icon-sprite.png
ReactXuexiZhidao/img/apple-touch-icon.png
ReactXuexiZhidao/img/cancelfullscreen.png
ReactXuexiZhidao/img/close.png
ReactXuexiZhidao/img/fullscreen.png
ReactXuexiZhidao/img/loader.gif
ReactXuexiZhidao/img/menu-icon.png
ReactXuexiZhidao/img/save.png
ReactXuexiZhidao/img/saved.png
ReactXuexiZhidao/img/settings-s.png
ReactXuexiZhidao/img/settings.png
ReactXuexiZhidao/img/star.png
ReactXuexiZhidao/js/__init__.py
ReactXuexiZhidao/js/epub.js
ReactXuexiZhidao/js/epub.min.js
ReactXuexiZhidao/js/epub.min.map
ReactXuexiZhidao/js/hooks.min.js
ReactXuexiZhidao/js/hooks.min.map
ReactXuexiZhidao/js/reader.js
ReactXuexiZhidao/js/reader.js.map
ReactXuexiZhidao/js/reader.min.js
ReactXuexiZhidao/js/reader.min.map
ReactXuexiZhidao/js/hooks/__init__.py
ReactXuexiZhidao/js/hooks/extensions/__init__.py
ReactXuexiZhidao/js/hooks/extensions/highlight.js
ReactXuexiZhidao/js/libs/__init__.py
ReactXuexiZhidao/js/libs/jquery.min.js
ReactXuexiZhidao/js/libs/localforage.min.js
ReactXuexiZhidao/js/libs/screenfull.js
ReactXuexiZhidao/js/libs/screenfull.min.js
ReactXuexiZhidao/js/libs/zip.min.js
ReactXuexiZhidao/js/plugins/__init__.py
ReactXuexiZhidao/js/plugins/hypothesis.js
ReactXuexiZhidao/js/plugins/search.js
react_xuexi_zhidao-2024.3.4.0.dist-info/METADATA
react_xuexi_zhidao-2024.3.4.0.dist-info/WHEEL
react_xuexi_zhidao-2024.3.4.0.dist-info/entry_points.txt
react_xuexi_zhidao-2024.3.4.0.dist-info/top_level.txt
react_xuexi_zhidao-2024.3.4.0.dist-info/RECORD
